grpcless/__init__.py
grpcless/__main__.py
grpcless/client/__init__.py
grpcless/client/pool.py
grpcless/engine/__init__.py
grpcless/engine/fill_abc.py
grpcless/engine/setio.py
grpcless/engine/utils.py
grpcless/import_fixer/__init__.py
grpcless/log/__init__.py
grpcless/log/color.py
grpcless/log/time.py
grpcless/middleware/__init__.py
grpcless/middleware/errortrace.py
grpcless/middleware/log.py
grpcless/printfix/__init__.py
grpcless/product_mode/__init__.py
grpcless/product_mode/build.py
grpcless/product_mode/copy.py
grpcless/proto/__init__.py
grpcless/proto/compile.py
grpcless/proto/import_pb.py
grpcless/proto/utils.py
grpcless/stream/__init__.py
grpcless/tools/__init__.py
grpcless/tools/main.py
grpcless-0.0.3.dist-info/LICENSE
grpcless-0.0.3.dist-info/METADATA
grpcless-0.0.3.dist-info/WHEEL
grpcless-0.0.3.dist-info/entry_points.txt
grpcless-0.0.3.dist-info/RECORD
