Metadata-Version: 2.3
Name: grpcless
Version: 0.0.3
Summary: grpcless Python GRPC Engine
License: MIT
Author: cxykevin
Author-email: cxykevin@yeah.net
Requires-Python: >=3.13
Classifier: License :: OSI Approved :: MIT License
Classifier: Programming Language :: Python :: 3
Classifier: Programming Language :: Python :: 3.13
Provides-Extra: runtime
Requires-Dist: grpcio-tools (==1.72.0rc1)
Requires-Dist: grpclib (>=0.4.8,<0.5.0)
Requires-Dist: mypy-protobuf (>=3.6.0,<4.0.0)
Requires-Dist: uvloop (>=0.21.0,<0.22.0) ; extra == "runtime"
